Workbook

Sheet Snippet
E4: Financial Analysis of Top 5 IT companies in India using SQL and EXCEL | FY2019 to FY2024
I7: Click To Navigate
E9: Growth Trends
E10: Profitability
E11: Market Position
E13: Financial Health
E15: Liquidity
E16: Company Snapshot
E18: IMT Charts
E19: Conclusion

Sheet Growth Trends
A1: Growth Trend Analysis
A3: Year-on-Year Revenue, Profit, & Operating Profit Growth(FY2019-24)
A5: Company | B5: Year | C5: Net Profit (Rs. Cr) | D5: Previous year Profit (Rs. Cr0 | E5: Operating Profit (Rs. Cr) | F5: Sales (Rs. Cr0 | G5: Pre. Year Sales(Rs. Cr) | H5: Profit Growth (%) | I5: Revenue Growth (%) | J5: Operating Profit Growth (%)
A6: HCL Tech | B6: 2019 | C6: 10120 | D6: - | E6: 14869 | F6: 60427 | G6: - | H6: - | I6: - | J6: -
A7: HCL Tech | B7: 2020 | C7: 11057 | D7: 10120 | E7: 17905 | F7: 70676 | G7: 60427 | H7: 9.26 | I7: 16.96 | J7: 20.42
A8: HCL Tech | B8: 2021 | C8: 11145 | D8: 11057 | E8: 20951 | F8: 75379 | G8: 70676 | H8: 0.8 | I8: 6.65 | J8: 17.01
A9: HCL Tech | B9: 2022 | C9: 13499 | D9: 11145 | E9: 21572 | F9: 85651 | G9: 75379 | H9: 21.12 | I9: 13.63 | J9: 2.96
A10: HCL Tech | B10: 2023 | C10: 14851 | D10: 13499 | E10: 23992 | F10: 101456 | G10: 85651 | H10: 10.02 | I10: 18.45 | J10: 11.22
A11: HCL Tech | B11: 2024 | C11: 15702 | D11: 14851 | E11: 25685 | F11: 109913 | G11: 101456 | H11: 5.73 | I11: 8.34 | J11: 7.06
A12: Infosys | B12: 2019 | C12: 15404 | D12: - | E12: 23046 | F12: 82675 | G12: - | H12: - | I12: - | J12: -
A13: Infosys | B13: 2020 | C13: 16594 | D13: 15404 | E13: 25025 | F13: 90791 | G13: 82675 | H13: 7.73 | I13: 9.82 | J13: 8.59
A14: Infosys | B14: 2021 | C14: 19351 | D14: 16594 | E14: 30018 | F14: 100472 | G14: 90791 | H14: 16.61 | I14: 10.66 | J14: 19.95
A15: Infosys | B15: 2022 | C15: 22110 | D15: 19351 | E15: 33750 | F15: 121641 | G15: 100472 | H15: 14.26 | I15: 21.07 | J15: 12.43
A16: Infosys | B16: 2023 | C16: 24095 | D16: 22110 | E16: 37818 | F16: 146767 | G16: 121641 | H16: 8.98 | I16: 20.66 | J16: 12.05
A17: Infosys | B17: 2024 | C17: 26233 | D17: 24095 | E17: 41121 | F17: 153670 | G17: 146767 | H17: 8.87 | I17: 4.7 | J17: 8.73
A18: TCS | B18: 2019 | C18: 31472 | D18: - | E18: 43727 | F18: 146463 | G18: - | H18: - | I18: - | J18: -
A19: TCS | B19: 2020 | C19: 32340 | D19: 31472 | E19: 46594 | F19: 156949 | G19: 146463 | H19: 2.76 | I19: 7.16 | J19: 6.56
A20: TCS | B20: 2021 | C20: 32430 | D20: 32340 | E20: 48330 | F20: 164177 | G20: 156949 | H20: 0.28 | I20: 4.61 | J20: 3.73
A21: TCS | B21: 2022 | C21: 38327 | D21: 32430 | E21: 56953 | F21: 191754 | G21: 164177 | H21: 18.18 | I21: 16.8 | J21: 17.84
A22: TCS | B22: 2023 | C22: 42147 | D22: 38327 | E22: 62552 | F22: 225458 | G22: 191754 | H22: 9.97 | I22: 17.58 | J22: 9.83
A23: TCS | B23: 2024 | C23: 45908 | D23: 42147 | E23: 67569 | F23: 240893 | G23: 225458 | H23: 8.92 | I23: 6.85 | J23: 8.02
A24: Tech Mahindra | B24: 2019 | C24: 4297.6 | D24: - | E24: 6814.4 | F24: 34742.1 | G24: - | H24: - | I24: - | J24: -
A25: Tech Mahindra | B25: 2020 | C25: 4033 | D25: 4297.6 | E25: 6831.1 | F25: 36867.7 | G25: 34742.1 | H25: -6.16 | I25: 6.12 | J25: 0.25
A26: Tech Mahindra | B26: 2021 | C26: 4428 | D26: 4033 | E26: 7659.6 | F26: 37855.1 | G26: 36867.7 | H26: 9.79 | I26: 2.68 | J26: 12.13
A27: Tech Mahindra | B27: 2022 | C27: 5566.1 | D27: 4428 | E27: 9071.1 | F27: 44646 | G27: 37855.1 | H27: 25.7 | I27: 17.94 | J27: 18.43
A28: Tech Mahindra | B28: 2023 | C28: 4831.3 | D28: 5566.1 | E28: 8702.1 | F28: 53290.2 | G28: 44646 | H28: -13.2 | I28: 19.36 | J28: -4.07
A29: Tech Mahindra | B29: 2024 | C29: 2357.8 | D29: 4831.3 | E29: 5394.7 | F29: 51995.5 | G29: 53290.2 | H29: -51.2 | I29: -2.43 | J29: -38.01
A30: Wipro | B30: 2019 | C30: 9003.7 | D30: - | E30: 14212.2 | F30: 59018.9 | G30: - | H30: - | I30: -
A31: Wipro | B31: 2020 | C31: 9722.3 | D31: 9003.7 | E31: 15020.7 | F31: 61137.6 | G31: 59018.9 | H31: 7.98 | I31: 3.59 | J31: 5.69
A32: Wipro | B32: 2021 | C32: 10796.4 | D32: 9722.3 | E32: 17103.5 | F32: 61934.9 | G32: 61137.6 | H32: 11.05 | I32: 1.3 | J32: 13.87
A33: Wipro | B33: 2022 | C33: 12229.6 | D33: 10796.4 | E33: 18737.3 | F33: 79312 | G33: 61934.9 | H33: 13.27 | I33: 28.06 | J33: 9.55
A34: Wipro | B34: 2023 | C34: 11350 | D34: 12229.6 | E34: 19097.1 | F34: 90487.6 | G34: 79312 | H34: -7.19 | I34: 14.09 | J34: 1.92
A35: Wipro | B35: 2024 | C35: 11045.2 | D35: 11350 | E35: 19316.4 | F35: 89760.3 | G35: 90487.6 | H35: -2.69 | I35: -0.8 | J35: 1.15

Sheet Profitability
A1: Profitability Analysis
A3: Year-on-year Net Profit Margin %, and Operating Profit Margin % (FY2019-24)
A5: Company | B5: Year | C5: Sales (Rs. Cr) | D5: Net Profit (Rs. Cr) | E5: Operating Profit (Rs. Cr) | F5: Net Profit Margin (%) | G5: Operating Profit Margin (%)
A6: HCL Tech | B6: 2019 | C6: 60427 | D6: 10120 | E6: 14869 | F6: 16.75 | G6: 24.61
A7: HCL Tech | B7: 2020 | C7: 70676 | D7: 11057 | E7: 17905 | F7: 15.64 | G7: 25.33
A8: HCL Tech | B8: 2021 | C8: 75379 | D8: 11145 | E8: 20951 | F8: 14.79 | G8: 27.79
A9: HCL Tech | B9: 2022 | C9: 85651 | D9: 13499 | E9: 21572 | F9: 15.76 | G9: 25.19
A10: HCL Tech | B10: 2023 | C10: 101456 | D10: 14851 | E10: 23992 | F10: 14.64 | G10: 23.65
A11: HCL Tech | B11: 2024 | C11: 109913 | D11: 15702 | E11: 25685 | F11: 14.29 | G11: 23.37
A12: Infosys | B12: 2019 | C12: 82675 | D12: 15404 | E12: 23046 | F12: 18.63 | G12: 27.88
A13: Infosys | B13: 2020 | C13: 90791 | D13: 16594 | E13: 25025 | F13: 18.28 | G13: 27.56
A14: Infosys | B14: 2021 | C14: 100472 | D14: 19351 | E14: 30018 | F14: 19.26 | G14: 29.88
A15: Infosys | B15: 2022 | C15: 121641 | D15: 22110 | E15: 33750 | F15: 18.18 | G15: 27.75
A16: Infosys | B16: 2023 | C16: 146767 | D16: 24095 | E16: 37818 | F16: 16.42 | G16: 25.77
A17: Infosys | B17: 2024 | C17: 153670 | D17: 26233 | E17: 41121 | F17: 17.07 | G17: 26.76
... A35: Wipro | B35: 2024 | C35: 89760.3 | D35: 11045.2 | E35: 19316.4 | F35: 12.31 | G35: 21.52

Sheet Market Position
A1: Market Position Analysis
A3: Revenue Market Share among Top 5 IT Companies (FY2019-24)
A5: Company | B5: Year | C5: Sales | D5: Revenue Market Share (%)
A6: TCS | B6: 2019 | C6: 146463 | D6: 38.21
A7: TCS | B7: 2020 | C7: 156949 | D7: 37.69
A8: TCS | B8: 2021 | C8: 164177 | D8: 37.33
A9: TCS | B9: 2024 | C9: 240893 | D9: 37.28
A10: TCS | B10: 2022 | C10: 191754 | D10: 36.66
A11: TCS | B11: 2023 | C11: 225458 | D11: 36.51
A12: Infosys | B12: 2024 | C12: 153670 | D12: 23.78
A13: Infosys | B13: 2023 | C13: 146767 | D13: 23.77
A14: Infosys | B14: 2022 | C14: 121641 | D14: 23.26
A15: Infosys | B15: 2021 | C15: 100472 | D15: 22.84
A16: Infosys | B16: 2020 | C16: 90791 | D16: 21.8
A17: Infosys | B17: 2019 | C17: 82675 | D17: 21.57
... A35: Tech Mahindra | B35: 2024 | C35: 51995.5 | D35: 8.05

Sheet Financial Health
A1: Financial Health Analysis
A3: Debt-to-Equity, ROE%, ROA%, Asset Turnover
A5: Company | B5: Year | C5: Borrowings (Rs. Cr) | D5: Shareholder Equity | E5: Net Profit (Rs. Cr) | F5: Total Assets (Rs. Cr) | G5: Debt-to-Equity | H5: ROE % | I5: ROA % | J5: Asset Turnover
A6: HCL Tech | B6: 2019 | C6: 4195 | D6: 41366 | E6: 10120 | F6: 58349 | G6: 0.1 | H6: 24.46 | I6: 17.34 | J6: 1.04
A7: HCL Tech | B7: 2020 | C7: 7986 | D7: 51267 | E7: 11057 | F7: 82819 | G7: 0.16 | H7: 21.57 | I7: 13.35 | J7: 0.85
A8: HCL Tech | B8: 2021 | C8: 6864 | D8: 59913 | E8: 11145 | F8: 86047 | G8: 0.11 | H8: 18.6 | I8: 12.95 | J8: 0.88
A9: HCL Tech | B9: 2022 | C9: 6343 | D9: 61914 | E9: 13499 | F9: 88921 | G9: 0.1 | H9: 21.8 | I9: 15.18 | J9: 0.96
A10: HCL Tech | B10: 2023 | C10: 4794 | D10: 65405 | E10: 14851 | F10: 93250 | G10: 0.07 | H10: 22.71 | I10: 15.93 | J10: 1.09
A11: HCL Tech | B11: 2024 | C11: 5758 | D11: 68263 | E11: 15702 | F11: 99006 | G11: 0.08 | H11: 23 | I11: 15.86 | J11: 1.11
A12: Infosys | B12: 2019 | C12: 4500 | D12: 64948 | E12: 15404 | F12: 84066 | G12: 0.07 | H12: 23.72 | I12: 18.32 | J12: 0.98
A13: Infosys | B13: 2020 | C13: 4633 | D13: 65450 | E13: 16594 | F13: 91800 | G13: 0.07 | H13: 25.35 | I13: 18.08 | J13: 0.99
A14: Infosys | B14: 2021 | C14: 5325 | D14: 76351 | E14: 19351 | F14: 107511 | G14: 0.07 | H14: 25.34 | I14: 18 | J14: 0.93
A15: Infosys | B15: 2022 | C15: 5474 | D15: 75350 | E15: 22110 | F15: 116729 | G15: 0.07 | H15: 29.34 | I15: 18.94 | J15: 1.04
A16: Infosys | B16: 2023 | C16: 8299 | D16: 75407 | E16: 24095 | F16: 124596 | G16: 0.11 | H16: 31.95 | I16: 19.34 | J16: 1.18
A17: Infosys | B17: 2024 | C17: 8359 | D17: 88116 | E17: 26233 | F17: 137360 | G17: 0.09 | H17: 29.77 | I17: 19.1 | J17: 1.12
... A35: Wipro | B35: 2024 | C35: 16464.9 | D35: 74988.3 | E35: 11045.2 | F35: 115064.2 | G35: 0.22 | H35: 14.73 | I35: 9.6 | J35: 0.78

Sheet Liquidity
A1: Liquidity Analysis
A3: Cash Ratio & Receivables-to-Revenue% (FY2016-24)
A5: Company | B5: Year | C5: Cash & Bank | D5: Total Liabilities (Rs. Cr) | E5: Receivables (Rs. Cr) | F5: Sales (Rs. Cr) | G5: Cash Ratio | H5: Receivables-to-Revenue(%)
A6: HCL Tech | B6: 2019 | C6: 7872 | D6: 58349 | E6: 11706 | F6: 60427 | G6: 0.13 | H6: 19.37
A7: HCL Tech | B7: 2020 | C7: 4976 | D7: 82819 | E7: 14131 | F7: 70676 | G7: 0.06 | H7: 19.99
A8: HCL Tech | B8: 2021 | C8: 8888 | D8: 86047 | E8: 17525 | F8: 75379 | G8: 0.1 | H8: 23.25
A9: HCL Tech | B9: 2022 | C9: 12636 | D9: 88921 | E9: 20671 | F9: 85651 | G9: 0.14 | H9: 24.13
A10: HCL Tech | B10: 2023 | C10: 14724 | D10: 93250 | E10: 25506 | F10: 101456 | G10: 0.16 | H10: 25.14
A11: HCL Tech | B11: 2024 | C11: 20150 | D11: 99006 | E11: 25521 | F11: 109913 | G11: 0.2 | H11: 23.22
A12: Infosys | B12: 2019 | C12: 19568 | D12: 84066 | E12: 14827 | F12: 82675 | G12: 0.23 | H12: 17.93
A13: Infosys | B13: 2020 | C13: 18649 | D13: 91800 | E13: 18487 | F13: 90791 | G13: 0.2 | H13: 20.36
A14: Infosys | B14: 2021 | C14: 24714 | D14: 107511 | E14: 19294 | F14: 100472 | G14: 0.23 | H14: 19.2
A15: Infosys | B15: 2022 | C15: 17472 | D15: 116729 | E15: 22698 | F15: 121641 | G15: 0.15 | H15: 18.66
A16: Infosys | B16: 2023 | C16: 12173 | D16: 124596 | E16: 25424 | F16: 146767 | G16: 0.1 | H16: 17.32
A17: Infosys | B17: 2024 | C17: 14786 | D17: 137360 | E17: 30193 | F17: 153670 | G17: 0.11 | H17: 19.65
... A35: Wipro | B35: 2024 | C35: 9695.3 | D35: 115064.2 | E35: 11547.7 | F35: 89760.3 | G35: 0.08 | H35: 12.87

Sheet Pivot Tables>

Sheet Profitability Trend Pivot
A3: Average of Net Profit Margin (%) | B3: Column Labels
A4: Row Labels | B4: TCS | C4: Infosys | D4: HCL Tech | E4: Wipro | F4: Tech Mahindra | G4: Grand Total
A5: 2019 | B5: 21.49 | C5: 18.63 | D5: 16.75 | E5: 15.26 | F5: 12.37 | G5: 16.9
A6: 2020 | B6: 20.61 | C6: 18.28 | D6: 15.64 | E6: 15.9 | F6: 10.94 | G6: 16.274
A7: 2021 | B7: 19.75 | C7: 19.26 | D7: 14.79 | E7: 17.43 | F7: 11.7 | G7: 16.586
A8: 2022 | B8: 19.99 | C8: 18.18 | D8: 15.76 | E8: 15.42 | F8: 12.47 | G8: 16.364
A9: 2023 | B9: 18.69 | C9: 16.42 | D9: 14.64 | E9: 12.54 | F9: 9.07 | G9: 14.272
A10: 2024 | B10: 19.06 | C10: 17.07 | D10: 14.29 | E10: 12.31 | F10: 4.53 | G10: 13.452
A11: Grand Total | B11: 19.931667 | C11: 17.973333 | D11: 15.311667 | E11: 14.81 | F11: 10.18 | G11: 15.641333
A33: Sum of Operating Profit (Rs. Cr) | B33: Column Labels
A34: Row Labels | B34: TCS | C34: Infosys | D34: HCL Tech | E34: Wipro | F34: Tech Mahindra | G34: Grand Total
A35: 2019 | B35: 43727 | C35: 23046 | D35: 14869 | E35: 14212.2 | F35: 6814.4 | G35: 102668.6
A36: 2020 | B36: 46594 | C36: 25025 | D36: 17905 | E36: 15020.7 | F36: 6831.1 | G36: 111375.8
A37: 2021 | B37: 48330 | C37: 30018 | D37: 20951 | E37: 17103.5 | F37: 7659.6 | G37: 124062.1
A38: 2022 | B38: 56953 | C38: 33750 | D38: 21572 | E38: 18737.3 | F38: 9071.1 | G38: 140083.4
A39: 2023 | B39: 62552 | C39: 37818 | D39: 23992 | E39: 19097.1 | F39: 8702.1 | G39: 152161.2
A40: 2024 | B40: 67569 | C40: 41121 | D40: 25685 | E40: 19316.4 | F40: 5394.7 | G40: 159086.1
A41: Grand Total | B41: 325725 | C41: 190778 | D41: 124974 | E41: 103487.2 | F41: 44473 | G41: 789437.2

Sheet Financial Health Pivot
A3: Average of ROE % | B3: Column Labels
A4: Row Labels | B4: TCS | C4: Infosys | D4: HCL Tech | E4: Tech Mahindra | F4: Wipro | G4: Grand Total
A5: 2019 | B5: 35.19 | C5: 23.72 | D5: 24.46 | E5: 21.19 | F5: 15.96 | G5: 24.104
A6: 2020 | B6: 38.44 | C6: 25.35 | D6: 21.57 | E6: 18.49 | F6: 17.57 | G6: 24.284
A7: 2021 | B7: 37.52 | C7: 25.34 | D7: 18.6 | E7: 17.81 | F7: 19.67 | G7: 23.788
A8: 2022 | B8: 43 | C8: 29.34 | D8: 21.8 | E8: 20.7 | F8: 18.7 | G8: 26.708
A9: 2023 | B9: 46.61 | C9: 31.95 | D9: 22.71 | E9: 17.3 | F9: 14.61 | G9: 26.636
A10: 2024 | B10: 50.73 | C10: 29.77 | D10: 23 | E10: 8.84 | F10: 14.73 | G10: 25.414
A11: Grand Total | B11: 41.915 | C11: 27.578333 | D11: 22.023333 | E11: 17.388333 | F11: 16.873333 | G11: 25.155667
A33: Sum of Debt-to-Equity | B33: Column Labels
A34: Row Labels | B34: Wipro | C34: Tech Mahindra | D34: HCL Tech | E34: Infosys | F34: TCS | G34: Grand Total
A35: 2019 | B35: 0.18 | C35: 0.1 | D35: 0.1 | E35: 0.07 | F35: 0 | G35: 0.45
A36: 2020 | B36: 0.18 | C36: 0.17 | D36: 0.16 | E36: 0.07 | F36: 0.1 | G36: 0.68
A37: 2021 | B37: 0.19 | C37: 0.12 | D37: 0.11 | E37: 0.07 | F37: 0.09 | G37: 0.58
A38: 2022 | B38: 0.27 | C38: 0.1 | D38: 0.1 | E38: 0.07 | F38: 0.09 | G38: 0.63
A39: 2023 | B39: 0.22 | C39: 0.1 | D39: 0.07 | E39: 0.11 | F39: 0.09 | G39: 0.59
A40: 2024 | B40: 0.22 | C40: 0.1 | D40: 0.08 | E40: 0.09 | F40: 0.09 | G40: 0.58
A41: Grand Total | B41: 1.26 | C41: 0.69 | D41: 0.62 | E41: 0.48 | F41: 0.46 | G41: 3.51

Sheet Growth Trend Pivot
A3: Average of Revenue Growth (%) | B3: Column Labels
A4: Row Labels | B4: HCL Tech | C4: Infosys | D4: TCS | E4: Tech Mahindra | F4: Wipro | G4: Grand Total
A5: 2019 | B5: #DIV/0! | C5: #DIV/0! | D5: #DIV/0! | E5: #DIV/0! | F5: #DIV/0! | G5: #DIV/0!
A6: 2020 | B6: 16.96 | C6: 9.82 | D6: 7.16 | E6: 6.12 | F6: 3.59 | G6: 8.73
A7: 2021 | B7: 6.65 | C7: 10.66 | D7: 4.61 | E7: 2.68 | F7: 1.3 | G7: 5.18
A8: 2022 | B8: 13.63 | C8: 21.07 | D8: 16.8 | E8: 17.94 | F8: 28.06 | G8: 19.5
A9: 2023 | B9: 18.45 | C9: 20.66 | D9: 17.58 | E9: 19.36 | F9: 14.09 | G9: 18.028
A10: 2024 | B10: 8.34 | C10: 4.7 | D10: 6.85 | E10: -2.43 | F10: -0.8 | G10: 3.332
A11: Grand Total | B11: 12.806 | C11: 13.382 | D11: 10.6 | E11: 8.734 | F11: 9.248 | G11: 10.954
A32: Average of Operating Profit Growth (%) | B32: Column Labels
A33: Row Labels | B33: HCL Tech | C33: Infosys | D33: TCS | E33: Tech Mahindra | F33: Wipro | G33: Grand Total
A34: 2019 | B34: #DIV/0! | C34: #DIV/0! | D34: #DIV/0! | E34: #DIV/0! | G34: #DIV/0!
A35: 2020 | B35: 20.42 | C35: 8.59 | D35: 6.56 | E35: 0.25 | F35: 5.69 | G35: 8.302
A36: 2021 | B36: 17.01 | C36: 19.95 | D36: 3.73 | E36: 12.13 | F36: 13.87 | G36: 13.338
A37: 2022 | B37: 2.96 | C37: 12.43 | D37: 17.84 | E37: 18.43 | F37: 9.55 | G37: 12.242
A38: 2023 | B38: 11.22 | C38: 12.05 | D38: 9.83 | E38: -4.07 | F38: 1.92 | G38: 6.19
A39: 2024 | B39: 7.06 | C39: 8.73 | D39: 8.02 | E39: -38.01 | F39: 1.15 | G39: -2.61
A40: Grand Total | B40: 11.734 | C40: 12.35 | D40: 9.196 | E40: -2.254 | F40: 6.436 | G40: 7.4924

Sheet Market Position Pivot
A3: Average of Revenue Market Share (%) | B3: Column Labels
A4: Row Labels | B4: HCL Tech | C4: Infosys | D4: TCS | E4: Tech Mahindra | F4: Wipro | G4: Grand Total
A5: 2019 | B5: 15.76 | C5: 21.57 | D5: 38.21 | E5: 9.06 | F5: 15.4 | G5: 20
A6: 2020 | B6: 16.97 | C6: 21.8 | D6: 37.69 | E6: 8.85 | F6: 14.68 | G6: 19.998
A7: 2021 | B7: 17.14 | C7: 22.84 | D7: 37.33 | E7: 8.61 | F7: 14.08 | G7: 20
A8: 2022 | B8: 16.38 | C8: 23.26 | D8: 36.66 | E8: 8.54 | F8: 15.16 | G8: 20
A9: 2023 | B9: 16.43 | C9: 23.77 | D9: 36.51 | E9: 8.63 | F9: 14.65 | G9: 19.998
A10: 2024 | B10: 17.01 | C10: 23.78 | D10: 37.28 | E10: 8.05 | F10: 13.89 | G10: 20.002
A11: Grand Total | B11: 16.615 | C11: 22.836667 | D11: 37.28 | E11: 8.6233333 | F11: 14.643333 | G11: 19.999667

Sheet Liquidity Pivot Table
A3: Sum of Cash Ratio | B3: Column Labels
A4: Row Labels | B4: HCL Tech | C4: Infosys | D4: TCS | E4: Tech Mahindra | F4: Wipro | G4: Grand Total
A5: 2019 | B5: 0.13 | C5: 0.23 | D5: 0.11 | E5: 0.07 | F5: 0.19 | G5: 0.73
A6: 2020 | B6: 0.06 | C6: 0.2 | D6: 0.08 | E6: 0.08 | F6: 0.18 | G6: 0.6
A7: 2021 | B7: 0.1 | C7: 0.23 | D7: 0.07 | E7: 0.07 | F7: 0.21 | G7: 0.68
A8: 2022 | B8: 0.14 | C8: 0.15 | D8: 0.13 | E8: 0.09 | F8: 0.1 | G8: 0.61
A9: 2023 | B9: 0.16 | C9: 0.1 | D9: 0.08 | E9: 0.09 | F9: 0.08 | G9: 0.51
A10: 2024 | B10: 0.2 | C10: 0.11 | D10: 0.09 | E10: 0.11 | F10: 0.08 | G10: 0.59
A11: Grand Total | B11: 0.79 | C11: 1.02 | D11: 0.56 | E11: 0.51 | F11: 0.84 | G11: 3.72

Sheet IMP Charts
A1: Some Imp Charts
A4: Growth Trends | M4: Profitability | Z4: Financial Health | AK4: Liquidity and Market Share

Sheet Company Snapshot
A1: Company Snapshot
A3: Key financial metrics summary for Each Company - FY2019-24
A5: Metric | B5: TCS | C5: Infosys | D5: HCL Tech | E5: Wipro | F5: Tech Mahindra | G5: Best | H5: Worst
A6: Revenue FY 2024 (Rs. Cr) | B6: =Liquidity!F23 -> 240893 | C6: =Liquidity!F17 -> 153670 | D6: =Liquidity!F11 -> 109913 | E6: =Liquidity!F35 -> 89760.3 | F6: =Liquidity!F29 -> 51995.5 | G6: TCS | H6: Tech Mahindra
A7: Revenue FY 2019 (Rs. Cr) | B7: =Liquidity!F18 -> 146463 | C7: =Liquidity!F12 -> 82675 | D7: =Liquidity!F6 -> 60427 | E7: =Liquidity!F30 -> 59018.9 | F7: =Liquidity!F24 -> 34742.1 | G7: TCS | H7: Tech Mahindra
A8: Net ProfitFY 2024 (Rs. Cr) | B8: ='Financial Health'!E23 -> 45908 | C8: ='Financial Health'!E17 -> 26233 | D8: ='Financial Health'!E11 -> 15702 | E8: ='Financial Health'!E35 -> 11045.2 | F8: ='Financial Health'!E29 -> 2357.8 | G8: TCS | H8: Tech Mahindra
A9: Net Margin % FY 2024 | B9: =Profitability!F23 -> 19.06 | C9: =Profitability!F17 -> 17.07 | D9: =Profitability!F11 -> 14.29 | E9: =Profitability!F35 -> 12.31 | F9: =Profitability!F29 -> 4.53 | G9: TCS | H9: Tech Mahindra
A10: Net Margin % FY 2019 | B10: =Profitability!F18 -> 21.49 | C10: =Profitability!F12 -> 18.63 | D10: =Table2[[#This Row],[Net Profit Margin (%)]] -> 14.64 | E10: =Profitability!F30 -> 15.26 | F10: =Profitability!F24 -> 12.37 | G10: TCS | H10: Tech Mahindra
A11: Operating Profit Margin % FY 2024 | B11: =Profitability!G23 -> 28.05 | C11: =Profitability!G17 -> 26.76 | D11: =Profitability!G11 -> 23.37 | E11: =Profitability!G35 -> 21.52 | F11: =Profitability!G29 -> 10.38 | G11: TCS | H11: Tech Mahindra
A12: ROE % FY2024 | B12: ='Financial Health'!H23 -> 50.73 | C12: ='Financial Health'!H17 -> 29.77 | D12: ='Financial Health'!H11 -> 23 | E12: ='Financial Health'!H35 -> 14.73 | F12: ='Financial Health'!H29 -> 8.84 | G12: TCS | H12: Tech Mahindra
A13: ROA % FY2024 | B13: ='Financial Health'!I23 -> 31.56 | C13: ='Financial Health'!I17 -> 19.1 | D13: ='Financial Health'!I11 -> 15.86 | E13: ='Financial Health'!I35 -> 9.6 | F13: ='Financial Health'!I29 -> 5.46 | G13: TCS | H13: Tech Mahindra
A14: Debt/Equity FY 2024 | B14: ='Financial Health'!G23 -> 0.09 | C14: ='Financial Health'!G17 -> 0.09 | D14: ='Financial Health'!G11 -> 0.08 | E14: ='Financial Health'!G35 -> 0.22 | F14: ='Financial Health'!G29 -> 0.1 | G14: HCL Tech | H14: Wipro
A15: Asset Turnover FY 2024 | B15: ='Financial Health'!J23 -> 1.66 | C15: ='Financial Health'!J17 -> 1.12 | D15: =Table3[[#This Row],[Asset Turnover]] -> 1.04 | E15: ='Financial Health'!J35 -> 0.78 | F15: ='Financial Health'!J29 -> 1.21 | G15: TCS | H15: Wipro
A16: Market Share % FY 2024 | B16: ='Market Position'!D9 -> 37.28 | C16: =Table4[[#This Row],[Revenue Market Share (%)]] -> 21.8 | D16: ='Market Position'!D19 -> 17.01 | E16: ='Market Position'!D29 -> 13.89 | F16: ='Market Position'!D35 -> 8.05 | G16: TCS | H16: Tech Mahindra
A17: Market Share % FY 2019 | B17: ='Market Position'!D6 -> 38.21 | C17: ='Market Position'!D17 -> 21.57 | D17: ='Market Position'!D23 -> 15.76 | E17: ='Market Position'!D24 -> 15.4 | F17: ='Market Position'!D30 -> 9.06 | G17: TCS | H17: Tech Mahindra
A18: Cash Ratio FY2024 | B18: =Liquidity!G23 -> 0.09 | C18: =Liquidity!G17 -> 0.11 | D18: =Liquidity!G11 -> 0.2 | E18: =Liquidity!G35 -> 0.08 | F18: =Liquidity!G29 -> 0.11 | G18: HCL Tech | H18: Wipro
A19: Receivables to Revenue % FY2024 | B19: =Liquidity!H23 -> 22.24 | C19: =Liquidity!H17 -> 19.65 | D19: =Liquidity!H11 -> 23.22 | E19: =Liquidity!H35 -> 12.87 | F19: =Liquidity!H29 -> 21.93 | G19: Wipro | H19: HCL Tech

Sheet Conclusion
A1: Study Coclusion and Key Findings
A3: Comparative financial analysis of India's Top 5 IT Companies | FY2019 to Fy 2024 |Data source: Screener.in
A5: Study Statement:
A6: A comparative financial analysis of India's Top 5 IT companies (TCS, Infosys, HCL Tech, Wipro, Tech Mahindra) over FY2019-2024, examining revenue and profit growth trends, financial health indicators, and competitive positioning to identify which firms demonstrated the strongest and most consistent performance.
A10: 1. TCS's Dominance is Unmatched
A11: TCS has led the every single metric consistently over 5 years; highest markrt share (36-38%), net margin(~20%), ROE (35-50%), ROA(above 27%), and operating margin (27-28%). It has the clear benchmark of Indian IT.
A15: 2. 2022 was a Universal Boom Year
A16: Every company posted double-digit profit growth in FY2022, singnaling a strong post-COVID recovery wave across the Indian IT sector driven by accelarated digital transformation spending globally.
A20: 3. HCL Tech is the Dark Horse
A21: HCL recorded the highest revenue growth among all five companies in FY2024(8.34%) while others slowed or declined. Its ROA has grown consistently from 17% to 15-16%, making it the strongest growth challenger.
A25: 4. Tech Mahindra is in Serious Trouble
A26: Tech Mahindra showed the alarming deterioration; net margin crashed to just 4.53% in FY2024, profit declined by 51.2%, and revenue growth was negative 2.43%. It is the only company with negative revenue growth in FY2024.
... A36: Among India's Top 5 IT companies over FY2019-2024, TCS maintained undisputed leadership across all financial metrics. HCL emerged as the strongest growth challenger in FY2024, while Tech Mahindra showed alarming deterioration in profitability. The sector demonstrated remarkable financial discipline with near-zero debt levels, and FY2022 marked a universal post-COVID earnings peak across all players.
